odoo10_addon_delivery_carrier_category-10.0.1.1.0-py3.6-nspkg.pth
odoo/addons/delivery_carrier_category/README.rst
odoo/addons/delivery_carrier_category/__init__.py
odoo/addons/delivery_carrier_category/__manifest__.py
odoo/addons/delivery_carrier_category/data/delivery_carrier_category.xml
odoo/addons/delivery_carrier_category/i18n/delivery_carrier_category.pot
odoo/addons/delivery_carrier_category/models/__init__.py
odoo/addons/delivery_carrier_category/models/delivery_carrier.py
odoo/addons/delivery_carrier_category/models/delivery_carrier_category.py
odoo/addons/delivery_carrier_category/readme/CONTRIBUTORS.rst
odoo/addons/delivery_carrier_category/readme/DESCRIPTION.rst
odoo/addons/delivery_carrier_category/readme/USAGE.rst
odoo/addons/delivery_carrier_category/security/delivery_carrier_category.xml
odoo/addons/delivery_carrier_category/static/description/icon.png
odoo/addons/delivery_carrier_category/static/description/index.html
odoo/addons/delivery_carrier_category/tests/__init__.py
odoo/addons/delivery_carrier_category/tests/test_carrier_category.py
odoo/addons/delivery_carrier_category/views/delivery_carrier.xml
odoo/addons/delivery_carrier_category/views/delivery_carrier_category.xml
odoo10_addon_delivery_carrier_category-10.0.1.1.0.dist-info/METADATA
odoo10_addon_delivery_carrier_category-10.0.1.1.0.dist-info/WHEEL
odoo10_addon_delivery_carrier_category-10.0.1.1.0.dist-info/namespace_packages.txt
odoo10_addon_delivery_carrier_category-10.0.1.1.0.dist-info/top_level.txt
odoo10_addon_delivery_carrier_category-10.0.1.1.0.dist-info/RECORD
